litestar_piccolo/__init__.py
litestar_piccolo/__metadata__.py
litestar_piccolo/dto.py
litestar_piccolo/plugin.py
litestar_piccolo/py.typed
litestar_piccolo-0.1.0.dist-info/METADATA
litestar_piccolo-0.1.0.dist-info/WHEEL
litestar_piccolo-0.1.0.dist-info/licenses/LICENSE
litestar_piccolo-0.1.0.dist-info/RECORD
