Metadata-Version: 2.1
Name: litestar-piccolo
Version: 0.1.0
Summary: Piccolo ORM plugin for Litestar
Project-URL: Changelog, https://litestar-org.github.io/litesatr-piccolo/latest/changelog
Project-URL: Discord, https://discord.gg/X3FJqy8d2j
Project-URL: Documentation, https://litestar-org.github.io/litesatr-piccolo/latest/
Project-URL: Homepage, https://litestar-org.github.io/litesatr-piccolo/latest/
Project-URL: Issue, https://github.com/litestar-org/litestar-piccolo/issues/
Project-URL: Source, https://github.com/litestar-org/litestar-piccolo
Author-email: Cody Fincher <cody.fincher@gmail.com>
License: MIT
License-File: LICENSE
Keywords: litestar,piccolo
Classifier: Development Status :: 3 - Alpha
Classifier: Environment :: Web Environment
Classifier: Intended Audience :: Developers
Classifier: Intended Audience :: System Administrators
Classifier: License :: OSI Approved :: MIT License
Classifier: Natural Language :: English
Classifier: Operating System :: OS Independent
Classifier: Programming Language :: Python
Classifier: Programming Language :: Python :: 3.8
Classifier: Programming Language :: Python :: 3.9
Classifier: Programming Language :: Python :: 3.10
Classifier: Programming Language :: Python :: 3.11
Classifier: Programming Language :: Python :: 3.12
Classifier: Topic :: Database
Classifier: Topic :: Database :: Database Engines/Servers
Classifier: Topic :: Software Development
Classifier: Typing :: Typed
Requires-Python: >=3.8
Requires-Dist: litestar[cli]>=2.0.1
Requires-Dist: piccolo
